Metadata-Version: 1.0
Name: gym-bit-flip
Version: 0.0.6
Summary: openai gym interface to bit flip problem described in Hindsight Experience Replay
Home-page: UNKNOWN
Author: Zach Dwiel
Author-email: zach.dwiel@intel.com
License: Apache
Platform: UNKNOWN
